edgesync360edgehubedgesdk/EdgeAgent.py
edgesync360edgehubedgesdk/EdgeAgentOld.py
edgesync360edgehubedgesdk/__init__.py
edgesync360edgehubedgesdk/Common/Constants.py
edgesync360edgehubedgesdk/Common/Converter.py
edgesync360edgehubedgesdk/Common/DataRecoverHelper.py
edgesync360edgehubedgesdk/Common/Logger.py
edgesync360edgehubedgesdk/Common/Topic.py
edgesync360edgehubedgesdk/Common/Utils.py
edgesync360edgehubedgesdk/Common/__init__.py
edgesync360edgehubedgesdk/Model/Edge.py
edgesync360edgehubedgesdk/Model/Event.py
edgesync360edgehubedgesdk/Model/Interface.py
edgesync360edgehubedgesdk/Model/MQTTMessage.py
edgesync360edgehubedgesdk/Model/__init__.py
edgesync360edgehubedgesdk/Model/MessageClient/AzureIotHub.py
edgesync360edgehubedgesdk/Model/MessageClient/Mqtt.py
edgesync360edgehubedgesdk/Model/MessageClient/__init__.py
EdgeSync360_EdgeHub_Edge_Python_SDK-1.0.2.1.dist-info/LICENSE
EdgeSync360_EdgeHub_Edge_Python_SDK-1.0.2.1.dist-info/METADATA
EdgeSync360_EdgeHub_Edge_Python_SDK-1.0.2.1.dist-info/WHEEL
EdgeSync360_EdgeHub_Edge_Python_SDK-1.0.2.1.dist-info/top_level.txt
EdgeSync360_EdgeHub_Edge_Python_SDK-1.0.2.1.dist-info/RECORD
