Metadata-Version: 2.1
Name: EdgeSync360_EdgeHub_Edge_Python_SDK
Version: 1.0.2.1
Summary: EdgeSync360_EdgeHub_Edge_Python_SDK package allows developers to write Python applications which access the EdgeSync360/EdgeHub Platform via MQTT protocol.
Home-page: https://github.com/EdgeHub-Repo/dc-edge-sdk-python-sample
Author: Paul Tseng
Author-email: edgehub.dev@gmail.com
Classifier: Programming Language :: Python :: 3
License-File: LICENSE
Requires-Dist: paho-mqtt==1.6.1
Requires-Dist: azure-iot-device
